netsweeper
